fibonacci/__init__.py
fibonacci/audit_logging.py
fibonacci/cli.py
fibonacci/cli_utils.py
fibonacci/client.py
fibonacci/config.py
fibonacci/constants.py
fibonacci/exceptions.py
fibonacci/keychain_storage.py
fibonacci/memory.py
fibonacci/nodes.py
fibonacci/secure_client.py
fibonacci/secure_config.py
fibonacci/tools_discovery.py
fibonacci/validators.py
fibonacci/workflow.py
fibonacci/yaml_exporter.py
fibonacci/yaml_loader.py
fibonacci_sdk-0.1.0.dist-info/METADATA
fibonacci_sdk-0.1.0.dist-info/WHEEL
fibonacci_sdk-0.1.0.dist-info/entry_points.txt
fibonacci_sdk-0.1.0.dist-info/licenses/LICENSE
fibonacci_sdk-0.1.0.dist-info/RECORD
