Metadata-Version: 2.4
Name: fibonacci-sdk
Version: 0.1.0
Summary: Python SDK for Fibonacci Workflow Automation Platform
License: Proprietary
License-File: LICENSE
Keywords: workflow,automation,ai,llm,orchestration
Author: Fibonacci Team
Author-email: team@fibonacci.today
Requires-Python: >=3.11,<4.0
Classifier: Development Status :: 3 - Alpha
Classifier: Intended Audience :: Developers
Classifier: License :: Other/Proprietary License
Classifier: Programming Language :: Python :: 3
Classifier: Programming Language :: Python :: 3.11
Classifier: Programming Language :: Python :: 3.12
Classifier: Programming Language :: Python :: 3.13
Classifier: Programming Language :: Python :: 3.14
Classifier: Topic :: Software Development :: Libraries :: Python Modules
Requires-Dist: httpx (>=0.27.0,<0.28.0)
Requires-Dist: pydantic (>=2.5.0,<3.0.0)
Requires-Dist: python-dotenv (>=1.0.0,<2.0.0)
Requires-Dist: pyyaml (>=6.0.1,<7.0.0)
Requires-Dist: rich (>=13.7.0,<14.0.0)
Requires-Dist: typer (>=0.12.0,<0.13.0)
Project-URL: Documentation, https://docs.fibonacci.today
Project-URL: Homepage, https://fibonacci.today
Project-URL: Repository, https://github.com/RohanBanerjee88/fibonacci-sdk
